django_magic/__init__.py
django_magic/routing.py
django_magic/settings.py
django_magic-0.5a0.dist-info/LICENSE
django_magic-0.5a0.dist-info/WHEEL
django_magic-0.5a0.dist-info/METADATA
django_magic-0.5a0.dist-info/RECORD
