Metadata-Version: 2.1
Name: django-magic
Version: 0.5a0
Summary: A collection of simple helpers and utilities for Django web development
License: AGPL-3.0-or-later
Author: Jeremy Potter
Author-email: git@stormdesign.us
Requires-Python: >=3.7,<4.0
Classifier: License :: OSI Approved :: GNU Affero General Public License v3 or later (AGPLv3+)
Classifier: Programming Language :: Python :: 3
Classifier: Programming Language :: Python :: 3.7
Classifier: Programming Language :: Python :: 3.8
Requires-Dist: dj_database_url (>=0.5.0,<0.6.0)
Requires-Dist: django (>=3.0.5,<4.0.0)
